pymodaq_plugins_arduino/__init__.py
pymodaq_plugins_arduino/utils.py
pymodaq_plugins_arduino/app/__init__.py
pymodaq_plugins_arduino/daq_move_plugins/__init__.py
pymodaq_plugins_arduino/daq_move_plugins/daq_move_LED.py
pymodaq_plugins_arduino/daq_move_plugins/daq_move_LEDwithLCD.py
pymodaq_plugins_arduino/daq_move_plugins/daq_move_Servo.py
pymodaq_plugins_arduino/daq_viewer_plugins/__init__.py
pymodaq_plugins_arduino/daq_viewer_plugins/plugins_0D/__init__.py
pymodaq_plugins_arduino/daq_viewer_plugins/plugins_0D/daq_0Dviewer_Analog.py
pymodaq_plugins_arduino/daq_viewer_plugins/plugins_1D/__init__.py
pymodaq_plugins_arduino/daq_viewer_plugins/plugins_2D/__init__.py
pymodaq_plugins_arduino/daq_viewer_plugins/plugins_ND/__init__.py
pymodaq_plugins_arduino/exporters/__init__.py
pymodaq_plugins_arduino/extensions/__init__.py
pymodaq_plugins_arduino/extensions/color_synthesizer.py
pymodaq_plugins_arduino/hardware/__init__.py
pymodaq_plugins_arduino/hardware/arduino_telemetrix.py
pymodaq_plugins_arduino/hardware/arduino_telemetrix_lcd.py
pymodaq_plugins_arduino/hardware/led_lcd.py
pymodaq_plugins_arduino/hardware/lcd_i2c/__init__.py
pymodaq_plugins_arduino/hardware/lcd_i2c/const.py
pymodaq_plugins_arduino/hardware/lcd_i2c/lcd_i2c.py
pymodaq_plugins_arduino/models/__init__.py
pymodaq_plugins_arduino/resources/ArduinoLED.xml
pymodaq_plugins_arduino/resources/ArduinoLEDMock.xml
pymodaq_plugins_arduino/resources/ArduinoLED_LCD.xml
pymodaq_plugins_arduino/resources/__init__.py
pymodaq_plugins_arduino/resources/config_template.toml
pymodaq_plugins_arduino/scanners/__init__.py
pymodaq_plugins_arduino-5.0.1.dist-info/METADATA
pymodaq_plugins_arduino-5.0.1.dist-info/WHEEL
pymodaq_plugins_arduino-5.0.1.dist-info/entry_points.txt
pymodaq_plugins_arduino-5.0.1.dist-info/licenses/LICENSE
pymodaq_plugins_arduino-5.0.1.dist-info/RECORD
